netlenium/__init__.py
netlenium/admin_client.py
netlenium/api.py
netlenium/client.py
netlenium/element.py
netlenium/exceptions.py
netlenium/proxy.py
netlenium/session.py
netlenium/types.py
netlenium/window.py
netlenium-1.0.0.2.dist-info/METADATA
netlenium-1.0.0.2.dist-info/WHEEL
netlenium-1.0.0.2.dist-info/top_level.txt
netlenium-1.0.0.2.dist-info/RECORD
