Metadata-Version: 2.1
Name: netlenium
Version: 1.0.0.2
Summary: Automate Web Browsers such as Chrome, Opera and Firefox  using Netlenium
Home-page: https://github.com/intellivoid/Netlenium-Python-Wrapper
Author: Intellivoid
Author-email: narrakas@intellivoid.info
License: UNKNOWN
Platform: UNKNOWN
